Workbook

Sheet Planilha1
A1: SIMULADOR DE INVESTIMENTO
B6: CONFIGURAÇÕES
B8: Salário | F8: 2000
B9: Rendimento da carteira | F9: 0.01
B10: Sugestão de Investimento (30%) | F10: =F8*30% -> 600
B12: INVESTIMENTO MENSAL
B14: Quanto investir por mês? | F14: =F8*0.1 -> 200
B15: Por quantos anos? | F15: 5
B16: Taxa de rendimento mensal | F16: 0.0108
B17: Patrimônio acumulado | F17: =FV(F16,F15*12,F14*-1) -> 16760.804
B18: Dividendos mensais | F18: =F17*F9 -> 167.60804
B20: CENÁRIOS | F20: Dividendo
A22: 2 | B22: Em 2 anos | D22: =FV($F$16,$A22*12,$F$14*-1) -> 5446.1727 | F22: =D22*$F$9 -> 54.461727
A23: 5 | B23: Em 5 anos | D23: =FV($F$16,$A23*12,$F$14*-1) -> 16760.804 | F23: =D23*$F$9 -> 167.60804
A24: 10 | B24: Em 10 anos | D24: =FV($F$16,$A24*12,$F$14*-1) -> 48691.533 | F24: =D24*$F$9 -> 486.91533
A25: 20 | B25: Em 20 anos | D25: =FV($F$16,$A25*12,$F$14*-1) -> 225409.8 | F25: =D25*$F$9 -> 2254.098
A26: 30 | B26: Em 30 anos | D26: =FV($F$16,$A26*12,$F$14*-1) -> 866780.96 | F26: =D26*$F$9 -> 8667.8096
B30: PERFIL | F30: CONSERVADOR
B31: VALOR A SER INVESTIDO POR MÊS | F31: 200
B33: TIPO DE FII | D33: PORCENTUAL SUGERIDO | F33: VALORES
B34: PAPEL | D34: =VLOOKUP($F$30&"-"&B34,Planilha2!$A:$D,4,FALSE) -> 0.3 | F34: =$F$31*D34 -> 60
B35: TIJOLO | D35: =VLOOKUP($F$30&"-"&B35,Planilha2!$A:$D,4,FALSE) -> 0.5 | F35: =$F$31*D35 -> 100
B36: HÍBRIDOS | D36: =VLOOKUP($F$30&"-"&B36,Planilha2!$A:$D,4,FALSE) -> 0.1 | F36: =$F$31*D36 -> 20
B37: FOFs | D37: =VLOOKUP($F$30&"-"&B37,Planilha2!$A:$D,4,FALSE) -> 0.1 | F37: =$F$31*D37 -> 20
B38: DESENVOLVIMENTO | D38: =VLOOKUP($F$30&"-"&B38,Planilha2!$A:$D,4,FALSE) -> 0 | F38: =$F$31*D38 -> 0
B39: HOTELARIA | D39: =VLOOKUP($F$30&"-"&B39,Planilha2!$A:$D,4,FALSE) -> 0 | F39: =$F$31*D39 -> 0
F40: =SUM(F34:G39) -> 200

Sheet Planilha2
A1: CHAVE | B1: PERFIL | C1: TIPO DE FII | D1: %
A2: =B2&"-"&C2 -> Conservador-PAPEL | B2: Conservador | C2: PAPEL | D2: 0.3
A3: =B3&"-"&C3 -> Conservador-TIJOLO | B3: Conservador | C3: TIJOLO | D3: 0.5
A4: =B4&"-"&C4 -> Conservador-HÍBRIDOS | B4: Conservador | C4: HÍBRIDOS | D4: 0.1
A5: =B5&"-"&C5 -> Conservador-FOFs | B5: Conservador | C5: FOFs | D5: 0.1
A6: =B6&"-"&C6 -> Conservador-DESENVOLVIMENTO | B6: Conservador | C6: DESENVOLVIMENTO | D6: 0
A7: =B7&"-"&C7 -> Conservador-HOTELARIA | B7: Conservador | C7: HOTELARIA | D7: 0
A8: =B8&"-"&C8 -> Moderado-PAPEL | B8: Moderado | C8: PAPEL | D8: 0.32
A9: =B9&"-"&C9 -> Moderado-TIJOLO | B9: Moderado | C9: TIJOLO | D9: 0.35
A10: =B10&"-"&C10 -> Moderado-HÍBRIDOS | B10: Moderado | C10: HÍBRIDOS | D10: 0.08
A11: =B11&"-"&C11 -> Moderado-FOFs | B11: Moderado | C11: FOFs | D11: 0.05
A12: =B12&"-"&C12 -> Moderado-DESENVOLVIMENTO | B12: Moderado | C12: DESENVOLVIMENTO | D12: 0.1
A13: =B13&"-"&C13 -> Moderado-HOTELARIA | B13: Moderado | C13: HOTELARIA | D13: 0.1
... A19: =B19&"-"&C19 -> Agressivo-HOTELARIA | B19: Agressivo | C19: HOTELARIA | D19: 0.1
